README.rst
setup.py
pysberbps/__init__.py
pysberbps/pysberbps.py
pysberbps/tests.py
pysberbps.egg-info/PKG-INFO
pysberbps.egg-info/SOURCES.txt
pysberbps.egg-info/dependency_links.txt
pysberbps.egg-info/requires.txt
pysberbps.egg-info/top_level.txt