Metadata-Version: 1.1
Name: pysberbps
Version: 0.0.1.dev1
Summary: Wrapper over Sberbank Acquiring API
Home-page: https://github.com/mnach/pysberbank
Author: Mikhail Nacharov
Author-email: mnach@ya.ru
License: BSD License
Keywords: acquiring sberbank bps processing E-Retail
Platform: UNKNOWN
Classifier: Development Status :: 3 - Alpha
Classifier: Intended Audience :: Developers
Classifier: License :: OSI Approved :: BSD License
Classifier: Programming Language :: Python :: 3.2
Classifier: Programming Language :: Python :: 3.3
Classifier: Programming Language :: Python :: 3.4
